email-forwarder/__init__.py
email-forwarder/email_forwarder.py
email_forwarder/__init__.py
email_forwarder/email_forwarder.py
email_forwarder-0.1.1.dist-info/METADATA
email_forwarder-0.1.1.dist-info/WHEEL
email_forwarder-0.1.1.dist-info/top_level.txt
email_forwarder-0.1.1.dist-info/zip-safe
email_forwarder-0.1.1.dist-info/RECORD
