Metadata-Version: 2.1
Name: email-forwarder
Version: 0.1.1
Summary: High level email forwarding in Python.
Home-page: https://github.com/wesinator/email-forwarder-python
Author: wesinator
License: UNKNOWN
Keywords: spam
Platform: UNKNOWN
Classifier: Development Status :: 4 - Beta
Classifier: Intended Audience :: Developers
Classifier: License :: OSI Approved :: GNU General Public License v3 or later (GPLv3+)
Classifier: Natural Language :: English
Classifier: Programming Language :: Python :: 3
Classifier: Programming Language :: Python :: 3.5
Classifier: Programming Language :: Python :: 3.6
Classifier: Programming Language :: Python :: 3.7
